LICENSE
sudoku_test/__init__.py
sudoku_test/config/__init__.py
sudoku_test/config/constants.py
sudoku_test/config/paths.py
sudoku_test/generation/sudoku_engine.py
sudoku_test/interface/__init__.py
sudoku_test/interface/command_line.py
sudoku_test/logs/__init__.py
sudoku_test/logs/setup_logging.py
sudoku_test/main.py
sudoku_test/py.typed
sudoku_test/VERSION
sudoku_test-0.1.1.dist-info/entry_points.txt
sudoku_test-0.1.1.dist-info/LICENSE
sudoku_test-0.1.1.dist-info/METADATA
sudoku_test-0.1.1.dist-info/WHEEL
sudoku_test-0.1.1.dist-info/RECORD
