Metadata-Version: 2.1
Name: sudoku_test
Version: 0.1.1
Summary: A sudoku project to test Blankslate.
Home-page: https://github.com/unkokaeru/sudoku_test
License: MIT
Author: W. Fayers
Author-email: wills@fayers.com
Requires-Python: >=3.8,<4.0
Classifier: License :: OSI Approved :: MIT License
Classifier: Programming Language :: Python :: 3
Classifier: Programming Language :: Python :: 3.8
Classifier: Programming Language :: Python :: 3.9
Classifier: Programming Language :: Python :: 3.10
Classifier: Programming Language :: Python :: 3.11
Classifier: Programming Language :: Python :: 3.12
Provides-Extra: dev
Provides-Extra: devlint
Provides-Extra: docs
Provides-Extra: lint
Provides-Extra: release
Provides-Extra: test
Provides-Extra: types
Requires-Dist: rich (>=12.0.0,<13.0.0)
Project-URL: Repository, https://github.com/unkokaeru/sudoku_test
